{
  "formatVersion": 1,
  "database": {
    "version": 1,
    "identityHash": "d8560b89dbf0f9416c8d7e729bc9d9a9",
    "entities": [
      {
        "tableName": "User",
        "createSql": "CREATE TABLE IF NOT EXISTS `${TABLE_NAME}` (`id` TEXT NOT NULL, `index` INTEGER NOT NULL, `email` TEXT NOT NULL, `passHash` TEXT NOT NULL, `lastLogin` TEXT, PRIMARY KEY(`id`))",
        "fields": [
          {
            "fieldPath": "id",
            "columnName": "id",
            "affinity": "TEXT",
            "notNull": true
          },
          {
            "fieldPath": "index",
            "columnName": "index",
            "affinity": "INTEGER",
            "notNull": true
          },
          {
            "fieldPath": "email",
            "columnName": "email",
            "affinity": "TEXT",
            "notNull": true
          },
          {
            "fieldPath": "passHash",
            "columnName": "passHash",
            "affinity": "TEXT",
            "notNull": true
          },
          {
            "fieldPath": "lastLogin",
            "columnName": "lastLogin",
            "affinity": "TEXT",
            "notNull": false
          }
        ],
        "primaryKey": {
          "columnNames": [
            "id"
          ],
          "autoGenerate": false
        },
        "indices": [],
        "foreignKeys": []
      },
      {
        "tableName": "Learn",
        "createSql": "CREATE TABLE IF NOT EXISTS `${TABLE_NAME}` (`id` INTEGER PRIMARY KEY AUTOINCREMENT NOT NULL, `userIndex` INTEGER NOT NULL, `type` INTEGER NOT NULL, `lvl4` TEXT NOT NULL, `kbd` TEXT NOT NULL, `sort1` INTEGER NOT NULL, `sort2` INTEGER NOT NULL, `time1` TEXT, `time2` TEXT, `easy1` INTEGER NOT NULL, `easy2` INTEGER NOT NULL, `tries1` INTEGER NOT NULL, `tries2` INTEGER NOT NULL)",
        "fields": [
          {
            "fieldPath": "id",
            "columnName": "id",
            "affinity": "INTEGER",
            "notNull": true
          },
          {
            "fieldPath": "userIndex",
            "columnName": "userIndex",
            "affinity": "INTEGER",
            "notNull": true
          },
          {
            "fieldPath": "type",
            "columnName": "type",
            "affinity": "INTEGER",
            "notNull": true
          },
          {
            "fieldPath": "lvl4",
            "columnName": "lvl4",
            "affinity": "TEXT",
            "notNull": true
          },
          {
            "fieldPath": "kbd",
            "columnName": "kbd",
            "affinity": "TEXT",
            "notNull": true
          },
          {
            "fieldPath": "sort1",
            "columnName": "sort1",
            "affinity": "INTEGER",
            "notNull": true
          },
          {
            "fieldPath": "sort2",
            "columnName": "sort2",
            "affinity": "INTEGER",
            "notNull": true
          },
          {
            "fieldPath": "time1",
            "columnName": "time1",
            "affinity": "TEXT",
            "notNull": false
          },
          {
            "fieldPath": "time2",
            "columnName": "time2",
            "affinity": "TEXT",
            "notNull": false
          },
          {
            "fieldPath": "easy1",
            "columnName": "easy1",
            "affinity": "INTEGER",
            "notNull": true
          },
          {
            "fieldPath": "easy2",
            "columnName": "easy2",
            "affinity": "INTEGER",
            "notNull": true
          },
          {
            "fieldPath": "tries1",
            "columnName": "tries1",
            "affinity": "INTEGER",
            "notNull": true
          },
          {
            "fieldPath": "tries2",
            "columnName": "tries2",
            "affinity": "INTEGER",
            "notNull": true
          }
        ],
        "primaryKey": {
          "columnNames": [
            "id"
          ],
          "autoGenerate": true
        },
        "indices": [],
        "foreignKeys": []
      }
    ],
    "setupQueries": [
      "CREATE TABLE IF NOT EXISTS room_master_table (id INTEGER PRIMARY KEY,identity_hash TEXT)",
      "INSERT OR REPLACE INTO room_master_table (id,identity_hash) VALUES(42, \"d8560b89dbf0f9416c8d7e729bc9d9a9\")"
    ]
  }
}